final/schematics/controller/librelane/controller.v
// Cause yosys to throw an error when we implicitly declare nets
`default_nettype none

// Simulation timestep
`timescale 1ns / 10ps

module controller #(
    parameter NUM_BITS = 8
  ) (
    input clk,
    input comp,
    input rst_n,
    output wire [NUM_BITS - 1:0] dac_in,
    output wire [NUM_BITS - 1:0] dac_in_n,
    output reg comparator_clk,
    output reg [NUM_BITS - 1:0] adc_out,
    output reg [$clog2(NUM_BITS):0] count
  );

  reg [NUM_BITS - 1:0] sar_reg;
  assign dac_in = sar_reg;
  assign dac_in_n = ~dac_in;

  //reg [$clog2(NUM_BITS):0] count;

  always @(posedge clk)
  begin
    if (!rst_n)
    begin
      count <= 0;
      sar_reg <= {1'b1, {(NUM_BITS - 1){1'b0}}};
      adc_out <= 0;
    end
    else
    begin
      if (count == (NUM_BITS))
      begin
        count <= 0;
        adc_out <= sar_reg;
        sar_reg <= {1'b1, {(NUM_BITS - 1){1'b0}}};
      end
      else if (comparator_clk)
      begin
        case (comp)
          1'b1:
            sar_reg[NUM_BITS - (count+1)] <= 0;
          1'b0:
            sar_reg[NUM_BITS - (count+1)] <= 1;
        endcase
        if ((count + 2) != (NUM_BITS + 1))
        begin
          sar_reg[NUM_BITS - (count + 2)] <= 1;
        end
        count <= count + 1;
      end
    end
  end

  always @(negedge clk)
  begin
    if (!rst_n)
    begin
      comparator_clk <= 0;
    end
    else
    begin
      comparator_clk <= !comparator_clk;
    end
  end

endmodule

final/schematics/controller/librelane/controller.vcd
$date
	Tue Dec 16 21:11:32 2025
$end
$version
	Icarus Verilog
$end
$timescale
	10ps
$end
$scope module controller $end
$var wire 1 ! clk $end
$var wire 1 " comp $end
$var wire 8 # dac_in_n [7:0] $end
$var wire 1 $ rst_n $end
$var wire 8 % dac_in [7:0] $end
$var parameter 32 & NUM_BITS $end
$var reg 8 ' adc_out [7:0] $end
$var reg 1 ( comparator_clk $end
$var reg 4 ) count [3:0] $end
$var reg 8 * sar_reg [7:0] $end
$upscope $end
$enddefinitions $end
$comment Show the parameter values. $end
$dumpall
b1000 &
$end
#0
$dumpvars
b10000000 *
b0 )
x(
b0 '
b10000000 %
0$
b1111111 #
z"
1!
$end
#2500
0(
0!
#5000
1!
#7500
0!
#10000
1!
#12500
0!
#15000
1!
#17500
0!
#20000
0"
1$
1!
#22500
1(
0!
#22600
1"
#25000
b10111111 #
b1 )
b1000000 %
b1000000 *
1!
#27500
0(
0!
#27600
0"
#30000
1!
#32500
1(
0!
#32600
1"
#35000
b11011111 #
b10 )
b100000 %
b100000 *
1!
#37500
0(
0!
#37600
0"
#40000
1!
#42500
1(
0!
#45000
b11001111 #
b11 )
b110000 %
b110000 *
1!
#47500
0(
0!
#50000
1!
#52500
1(
0!
#52600
1"
#55000
b11010111 #
b100 )
b101000 %
b101000 *
1!
#57500
0(
0!
#57600
0"
#60000
1!
#62500
1(
0!
#62600
1"
#65000
b11011011 #
b101 )
b100100 %
b100100 *
1!
#67500
0(
0!
#67600
0"
#70000
1!
#72500
1(
0!
#75000
b11011001 #
b110 )
b100110 %
b100110 *
1!
#77500
0(
0!
#80000
1!
#82500
1(
0!
#85000
b11011000 #
b111 )
b100111 %
b100111 *
1!
#87500
0(
0!
#90000
1!
#92500
1(
0!
#95000
b1000 )
1!
#97500
0(
0!
#100000
b1111111 #
b10000000 %
b10000000 *
b100111 '
b0 )
1!
#102500
1(
0!
#102600
1"
#105000
b10111111 #
b1 )
b1000000 %
b1000000 *
1!
#107500
0(
0!
#107600
0"
#110000
1!
#112500
1(
0!
#112600
1"
#115000
b11011111 #
b10 )
b100000 %
b100000 *
1!
#117500
0(
0!
#117600
0"
#120000
1!
#122500
1(
0!
#125000
b11001111 #
b11 )
b110000 %
b110000 *
1!
#127500
0(
0!
#130000
1!
#132500
1(
0!
#132600
1"
#135000
b11010111 #
b100 )
b101000 %
b101000 *
1!
#137500
0(
0!
#137600
0"
#140000
1!
#142500
1(
0!
#142600
1"
#145000
b11011011 #
b101 )
b100100 %
b100100 *
1!
#147500
0(
0!
#147600
0"
#150000
1!
#152500
1(
0!
#155000
b11011001 #
b110 )
b100110 %
b100110 *
1!
#157500
0(
0!
#160000
1!
#162500
1(
0!
#165000
b11011000 #
b111 )
b100111 %
b100111 *
1!
#167500
0(
0!
#170000
1!
#172500
1(
0!
#175000
b1000 )
1!
#177500
0(
0!
#180000
b1111111 #
b10000000 %
b10000000 *
b0 )
1!
#182500
1(
0!
#182600
1"
#185000
b10111111 #
b1 )
b1000000 %
b1000000 *
1!
#187500
0(
0!
#187600
0"
#190000
1!
#192500
1(
0!
#192600
1"
#195000
b11011111 #
b10 )
b100000 %
b100000 *
1!
#197500
0(
0!
#197600
0"
#200000
1!
#202500
1(
0!
#205000
b11001111 #
b11 )
b110000 %
b110000 *
1!
#207500
0(
0!
#210000
1!
#212500
1(
0!
#212600
1"
#215000
b11010111 #
b100 )
b101000 %
b101000 *
1!
#217500
0(
0!
#217600
0"
#220000
1!
#222500
1(
0!
#225000
b11010011 #
b101 )
b101100 %
b101100 *
1!
#227500
0(
0!
#230000
1!
#232500
1(
0!
#235000
b11010001 #
b110 )
b101110 %
b101110 *
1!
