final/schematics/controller/librelane/controller.v
// Cause yosys to throw an error when we implicitly declare nets
`default_nettype none

// Simulation timestep
`timescale 1ns / 10ps

module controller #(
    parameter NUM_BITS = 8
  ) (
    input clk,
    input comp,
    input rst_n,
    output wire [NUM_BITS - 1:0] dac_in,
    output wire [NUM_BITS - 1:0] dac_in_n,
    output reg comparator_clk,
    output reg [NUM_BITS - 1:0] adc_out
  );

  reg [NUM_BITS - 1:0] sar_reg;
  assign dac_in = sar_reg;
  assign dac_in_n = ~dac_in;

  reg [$clog2(NUM_BITS):0] count;

  always @(posedge clk)
  begin
    if (!rst_n)
    begin
      count <= 0;
      sar_reg <= {1'b1, {(NUM_BITS - 1){1'b0}}};
    end
    else
      if (count == (NUM_BITS))
      begin
        count <= 0;
        adc_out <= sar_reg;
        sar_reg <= {1'b1, {(NUM_BITS - 1){1'b0}}};
      end
      else
        if (comparator_clk)
        begin
          case (comp)
            1'b1:
              sar_reg[NUM_BITS - (count+1)] <= 0;
            1'b0:
              sar_reg[NUM_BITS - (count+1)] <= 1;
          endcase
          sar_reg[NUM_BITS - (count + 2)] <= 1;
          count <= count + 1;
        end
  end

  always @(negedge clk)
  begin
    if (!rst_n)
    begin
      comparator_clk <= 0;
    end
    else
    begin
      comparator_clk <= !comparator_clk;
    end
  end

endmodule

final/schematics/controller/librelane/controller.vcd
$date
	Mon Dec  8 11:43:53 2025
$end
$version
	Icarus Verilog
$end
$timescale
	10ps
$end
$scope module controller $end
$var wire 1 ! clk $end
$var wire 1 " comp $end
$var wire 8 # dac_in_n [7:0] $end
$var wire 1 $ rst_n $end
$var wire 8 % dac_in [7:0] $end
$var parameter 32 & NUM_BITS $end
$var reg 8 ' adc_out [7:0] $end
$var reg 1 ( comparator_clk $end
$var reg 4 ) count [3:0] $end
$var reg 8 * sar_reg [7:0] $end
$upscope $end
$enddefinitions $end
$comment Show the parameter values. $end
$dumpall
b1000 &
$end
#0
$dumpvars
b10000000 *
b0 )
x(
bx '
b10000000 %
0$
b1111111 #
z"
1!
$end
#2500
0(
0!
#5000
1!
#7500
0!
#10000
1!
#12500
0!
#15000
1!
#17500
0!
#20000
0"
1$
1!
#22500
1(
0!
#25000
b111111 #
b1 )
b11000000 %
b11000000 *
1!
#25100
1"
#27500
0(
0!
#30000
1!
#32500
1(
0!
#35000
b1011111 #
b10 )
b10100000 %
b10100000 *
1!
#35100
0"
#37500
0(
0!
#40000
1!
#42500
1(
0!
#45000
b1001111 #
b11 )
b10110000 %
b10110000 *
1!
#47500
0(
0!
#50000
1!
#52500
1(
0!
#55000
b1000111 #
b100 )
b10111000 %
b10111000 *
1!
#57500
0(
0!
#60000
1!
#62500
1(
0!
#65000
b1000011 #
b101 )
b10111100 %
b10111100 *
1!
#65100
1"
#67500
0(
0!
#70000
1!
#72500
1(
0!
#75000
b1000101 #
b110 )
b10111010 %
b10111010 *
1!
#77500
0(
0!
#80000
1!
#82500
1(
0!
#85000
b1000110 #
b111 )
b10111001 %
b10111001 *
1!
#85100
0"
#87500
0(
0!
#90000
1!
#92500
1(
0!
#95000
b1000 )
1!
#97500
0(
0!
#100000
b1111111 #
b10000000 %
b10000000 *
b10111001 '
b0 )
1!
#100100
1"
#102500
1(
0!
#105000
b10111111 #
b1 )
b1000000 %
b1000000 *
1!
#107500
0(
0!
#110000
1!
#112500
1(
0!
#115000
b11011111 #
b10 )
b100000 %
b100000 *
1!
#117500
0(
0!
#120000
1!
#122500
1(
0!
#125000
b11101111 #
b11 )
b10000 %
b10000 *
1!
#125100
0"
#127500
0(
0!
#130000
1!
#132500
1(
0!
#135000
b11100111 #
b100 )
b11000 %
b11000 *
1!
#135100
1"
#137500
0(
0!
#140000
1!
#142500
1(
0!
#145000
b11101011 #
b101 )
b10100 %
b10100 *
1!
#145100
0"
#147500
0(
0!
#150000
1!
#152500
1(
0!
#155000
b11101001 #
b110 )
b10110 %
b10110 *
1!
#155100
1"
#157500
0(
0!
#160000
1!
#162500
1(
0!
#165000
b11101010 #
b111 )
b10101 %
b10101 *
1!
#167500
0(
0!
#170000
1!
#172500
1(
0!
#175000
b11101011 #
b1000 )
b10100 %
b10100 *
1!
#175100
0"
#177500
0(
0!
#180000
b1111111 #
b10000000 %
b10000000 *
b10100 '
b0 )
1!
#180100
1"
